<databaseChangeLog
		xmlns="http://www.liquibase.org/xml/ns/dbchangelog/1.1"
		xmlns:xsi="http://www.w3.org/2001/XMLSchema-instance"
		xsi:schemaLocation="http://www.liquibase.org/xml/ns/dbchangelog/1.1
    http://www.liquibase.org/xml/ns/dbchangelog/dbchangelog-1.1.xsd">
	<changeSet author="liutkvai" id="data-1">
		<insert tableName="doctor">
			<column name="id">1</column>
			<column name="code">AKM-123</column>
			<column name="first_name">Ona-Laimutė</column>
			<column name="last_name">Liutkienė</column>
			<column name="occupation">Šeimos gydytoja</column>
		</insert>
	</changeSet>
	<changeSet author="liutkvai" id="data-2">
		<insert tableName="user">
			<column name="id">1</column>
			<column name="username">lailiutk@gmail.com</column>
			<column name="password">$2a$12$hrC3TcEut3NEqeVt.bmdI..LCVafwcwpXe7adIUB/zGqxF1WDL7WS</column>
			<column name="doctor_id">1</column>
		</insert>
	</changeSet>
</databaseChangeLog>